grafana_loki_push/__init__.py
grafana_loki_push/cli.py
grafana_loki_push/docker-compose.yml
grafana_loki_push/loki_client.py
grafana_loki_push/loki_deployment.py
grafana_loki_push/loki_handler.py
grafana_loki_push/config/__init__.py
grafana_loki_push/config/grafana-datasources.yml
grafana_loki_push/config/loki-config.yml
grafana_loki_push-1.0.4.dist-info/METADATA
grafana_loki_push-1.0.4.dist-info/WHEEL
grafana_loki_push-1.0.4.dist-info/entry_points.txt
grafana_loki_push-1.0.4.dist-info/top_level.txt
grafana_loki_push-1.0.4.dist-info/RECORD
