Metadata-Version: 2.4
Name: grafana-loki-push
Version: 1.0.4
Summary: 一键部署 Grafana Loki 系统，支持 HTTP 直接推送日志，无需 Promtail
Home-page: https://github.com/wersling/grafana-loki-push
Author: SeanZou
Author-email: SeanZou <wersling@gmail.com>
Maintainer-email: SeanZou <wersling@gmail.com>
License: MIT
Project-URL: Homepage, https://github.com/wersling/grafana-loki-push
Project-URL: Documentation, https://github.com/wersling/grafana-loki-push#readme
Project-URL: Repository, https://github.com/wersling/grafana-loki-push
Project-URL: Bug Tracker, https://github.com/wersling/grafana-loki-push/issues
Project-URL: Changelog, https://github.com/wersling/grafana-loki-push/releases
Keywords: grafana,loki,logging,loguru,observability,monitoring,logs,docker,http-push,prometheus
Platform: any
Classifier: Development Status :: 4 - Beta
Classifier: Intended Audience :: Developers
Classifier: Intended Audience :: System Administrators
Classifier: License :: OSI Approved :: MIT License
Classifier: Operating System :: OS Independent
Classifier: Programming Language :: Python :: 3
Classifier: Programming Language :: Python :: 3.8
Classifier: Programming Language :: Python :: 3.9
Classifier: Programming Language :: Python :: 3.10
Classifier: Programming Language :: Python :: 3.11
Classifier: Programming Language :: Python :: 3.12
Classifier: Topic :: Software Development :: Libraries :: Python Modules
Classifier: Topic :: System :: Logging
Classifier: Topic :: System :: Monitoring
Classifier: Topic :: System :: Systems Administration
Requires-Python: >=3.8
Requires-Dist: requests>=2.31.0
Requires-Dist: loguru>=0.7.2
Requires-Dist: pyyaml>=6.0.1
Requires-Dist: click>=8.1.7
Requires-Dist: python-json-logger>=2.0.7
Provides-Extra: dev
Requires-Dist: pytest>=7.4.4; extra == "dev"
Requires-Dist: pytest-cov>=4.1.0; extra == "dev"
Requires-Dist: black>=23.12.1; extra == "dev"
Requires-Dist: flake8>=6.1.0; extra == "dev"
Requires-Dist: mypy>=1.8.0; extra == "dev"
Provides-Extra: build
Requires-Dist: setuptools>=69.0.3; extra == "build"
Requires-Dist: wheel>=0.42.0; extra == "build"
Requires-Dist: build>=1.0.0; extra == "build"
Requires-Dist: twine>=4.0.0; extra == "build"
Provides-Extra: all
Requires-Dist: pytest>=7.4.4; extra == "all"
Requires-Dist: pytest-cov>=4.1.0; extra == "all"
Requires-Dist: black>=23.12.1; extra == "all"
Requires-Dist: flake8>=6.1.0; extra == "all"
Requires-Dist: mypy>=1.8.0; extra == "all"
Requires-Dist: setuptools>=69.0.3; extra == "all"
Requires-Dist: wheel>=0.42.0; extra == "all"
Requires-Dist: build>=1.0.0; extra == "all"
Requires-Dist: twine>=4.0.0; extra == "all"
Dynamic: author
Dynamic: home-page
Dynamic: platform
Dynamic: requires-python
